.DS_Store
rcj/.DS_Store
rcj/__init__.py
rcj/cryptosystem/__init__.py
rcj/cryptosystem/rsa.py
rcj/utility/__init__.py
rcj/utility/inputchecker.py
rcj/utility/rmath.py
rsa_jpv-1.0.3.dist-info/LICENSE
rsa_jpv-1.0.3.dist-info/METADATA
rsa_jpv-1.0.3.dist-info/WHEEL
rsa_jpv-1.0.3.dist-info/top_level.txt
rsa_jpv-1.0.3.dist-info/RECORD
