Metadata-Version: 2.1
Name: rsa-jpv
Version: 1.0.3
Summary: A 2048-bit RSA library that operates solely on integers.
Home-page: https://github.com/jpvitan/rsa-jpv
Author: Justine Paul Sanchez Vitan
Author-email: justinepaulvitan5@gmail.com
License: UNKNOWN
Platform: UNKNOWN
Classifier: Programming Language :: Python :: 3
Classifier: License :: OSI Approved :: GNU General Public License v3 (GPLv3)
Classifier: Operating System :: OS Independent
Requires-Python: >=3.6
License-File: LICENSE
